aico/__init__.py
aico/__main__.py
aico/backup.py
aico/bootstrap.py
aico/chat.py
aico/cli_ui.py
aico/const.py
aico/core.py
aico/diff.py
aico/file_processing.py
aico/gen.py
aico/git.py
aico/main.py
aico/stats.py
aico/tpl/ask.j2
aico/tpl/cr-file-gen-changes.j2
aico/tpl/describe.j2
aico/tpl/file-review-full-content.j2
aico/tpl/file-review.j2
aico/tpl/gen/ask.j2
aico/tpl/gen/make-td.j2
aico/tpl/gen/part/expected-file-operations.j2
aico/tpl/gen/part/work-context.j2
aico/tpl/gen/work.j2
aico/tpl/one-improvement.j2
aico/tpl/part/do-code-review.j2
aico/tpl/part/do-proofreading.j2
aico/tpl/part/expect-implement.j2
aico/tpl/part/file-expect-sections.j2
aico/tpl/part/you.j2
aico/tpl/project/file_names.j2
aico/tpl/project/files.j2
aico/tpl/project/gen/file_names.j2
aico/tpl/project/gen/files.j2
aico/tpl/project/meta-main.j2
aico/tpl/propose.j2
aico/tpl/self-estimate-changes.j2
aico/tpl/task-update-file.j2
aico/tpl/work/work.j2
aico/utils.py
aico_cli-0.1.5.dist-info/entry_points.txt
aico_cli-0.1.5.dist-info/LICENSE
aico_cli-0.1.5.dist-info/METADATA
aico_cli-0.1.5.dist-info/WHEEL
aico_cli-0.1.5.dist-info/RECORD
