Metadata-Version: 2.3
Name: aico-cli
Version: 0.1.5
Summary: AI coding assistant
License: MIT
Keywords: ai,coding,assistant,llm,vibe-coding
Author: Nayjest
Author-email: mail@vitaliy.in
Requires-Python: >=3.11,<4.0
Classifier: Development Status :: 4 - Beta
Classifier: Environment :: Console
Classifier: Intended Audience :: Developers
Classifier: License :: OSI Approved :: MIT License
Classifier: Programming Language :: Python :: 3
Classifier: Programming Language :: Python :: 3.11
Classifier: Programming Language :: Python :: 3.12
Classifier: Programming Language :: Python :: 3.13
Classifier: Topic :: Software Development :: Code Generators
Requires-Dist: ai-microcore (>=4.0.0.dev3,<5.0.0)
Requires-Dist: anthropic (>=0.49.0,<0.50.0)
Requires-Dist: colorama (>=0.4.6,<0.5.0)
Requires-Dist: flask (>=3.1.0,<4.0.0)
Requires-Dist: google-generativeai (>=0.8.5,<0.9.0)
Requires-Dist: openai (>=1.75.0,<2.0.0)
Requires-Dist: patch (>=1.16.0,<2.0.0)
Requires-Dist: rich (>=13.9.4,<14.0.0)
Requires-Dist: typer (>=0.15.1,<0.16)
Project-URL: Homepage, https://github.com/Nayjest/aico
Project-URL: Repository, https://github.com/Nayjest/aico
